{"type": "Feature", "id": 12517578, "properties": {"woe:id": 12517578, "woe:parent_id": 778024, "woe:name": "Aeropuerto de Valladolid", "woe:placetype": 14, "woe:placetype_name": "Airport", "woe:lang": "SPA", "iso:country": "ES", "meta:provider": ["geoplanet:7.3.1", "geoplanet:7.3.2", "geoplanet:7.4.0", "geoplanet:7.4.1", "geoplanet:7.5.1", "geoplanet:7.5.2", "geoplanet:7.6.0", "geoplanet:7.8.1", "geoplanet:7.9.0", "geoplanet:7.10.0", "geoplanet:8.0.0", "woeplanet:8.0.0"], "meta:indexed": "2020-08-20T20:56:08.206158", "woe:alias_FIN_V": ["Valladolid Lentokentta", "Valladolid Lentokentt\u00e4"], "woe:alias_ENG_V": ["VLL Airport", "VLL"], "woe:alias_ITA_V": ["Aeroporto Di Valladolid"], "woe:alias_ENG_P": ["Valladolid Airport"], "woe:alias_DAN_V": ["Valladolid Lufthavn"], "woe:alias_UNK_V": ["Letiste Valladolid", "Letisko Valladolid"], "woe:alias_DUT_V": ["Luchthaven Valladolid"], "woe:alias_POR_V": ["Aeroporto de Valladolid"], "woe:alias_SWE_V": ["Valladolid Flygplats"], "meta:updated": "2020-08-22T03:00:09.586885", "woe:alias_SPA_S": ["Aeropuerto de Valladolid"], "woe:alias_GER_V": ["Flughafen Valladolid"], "woe:alias_FRE_V": ["Aeroport de Valladolid", "A\u00e9roport de Valladolid"], "woe:alias_SPA_V": ["Aeropuerto Valladolid", "Aeropuerto VLL", "VLL Aeropuerto", "Aeropuerto de Villanubla"], "woe:alias_FIN_S": ["Valladolid Lentokentta"], "woe:alias_FRE_Q": ["A\u00e9roport de Valladolid"], "woe:alias_FIN_Q": ["Valladolid Lentokentt\u00e4"], "woe:alias_DUT_Q": ["Luchthaven Valladolid"], "woe:alias_GER_Q": ["Flughafen Valladolid"], "woe:alias_FRE_S": ["Aeroport de Valladolid"], "woe:alias_POR_Q": ["Aeroporto de Valladolid"], "woe:alias_DAN_Q": ["Valladolid Lufthavn"], "woe:alias_SWE_Q": ["Valladolid Flygplats"], "woe:alias_UNK_Q": ["Letiste Valladolid", "Letisko Valladolid"], "woe:alias_ITA_Q": ["Aeroporto Di Valladolid"], "woe:hierarchy": {"continent": 24865675, "country": 23424950, "town": 0, "planet": 1, "county": 12602122, "suburb": 0, "state": 12578033, "region": 0, "localadmin": 12693111}, "woe:timezone_id": 56043644, "woe:hash": "ezkt3b277emk", "woe:centroid": [-4.84447, 41.706051], "geom:latitude": 41.706051, "geom:longitude": -4.84447, "geom:hash": "ezkt3b277emk", "woe:latitude": 41.706051, "geom:centroid": [-4.84447, 41.706051], "woe:longitude": -4.84447, "woe:repo": "woeplanet-airport-es"}, "geometry": {"coordinates": [-4.84447, 41.706051], "type": "Point"}}