{"type": "Feature", "id": 12517554, "geometry": {"type": "Point", "coordinates": [-7.4603, 43.1189]}, "properties": {"woe:id": 12517554, "woe:parent_id": 55866632, "woe:name": "Lugo Airport", "woe:placetype": 14, "woe:placetype_name": "Airport", "woe:lang": "ENG", "iso:country": "ES", "meta:provider": ["geoplanet:7.3.1", "geoplanet:7.3.2", "geoplanet:7.4.0", "geoplanet:7.4.1", "geoplanet:7.5.1", "geoplanet:7.5.2", "geoplanet:7.6.0", "geoplanet:7.8.1", "geoplanet:7.9.0", "geoplanet:7.10.0", "geoplanet:8.0.0", "woeplanet:8.0.0"], "meta:indexed": "2020-08-20T20:56:08.164928", "meta:updated": "2020-10-14T11:07:19.168543", "woe:hierarchy": {"continent": 24865675, "country": 23424950, "town": 0, "planet": 1, "county": 12602131, "suburb": 0, "state": 12578036, "region": 0, "localadmin": 12694807}, "woe:timezone_id": 56043644, "woe:hash": "ezdtq1x9f3t1", "woe:centroid": [-7.4603, 43.1189], "geom:latitude": 43.1189, "geom:longitude": -7.4603, "geom:hash": "ezdtq1x9f3t1", "woe:latitude": 43.1189, "geom:centroid": [-7.4603, 43.1189], "woe:longitude": -7.4603, "woe:repo": "woeplanet-airport-es", "geom:area": 0.0, "woe:scale": 19}}