{"type": "Feature", "id": 12517562, "geometry": {"type": "Point", "coordinates": [-1.63952, 42.76754]}, "properties": {"woe:id": 12517562, "woe:parent_id": 768421, "woe:name": "Aeropuerto de Pamplona", "woe:placetype": 14, "woe:placetype_name": "Airport", "woe:lang": "SPA", "iso:country": "ES", "meta:provider": ["geoplanet:7.3.1", "geoplanet:7.3.2", "geoplanet:7.4.0", "geoplanet:7.4.1", "geoplanet:7.5.1", "geoplanet:7.5.2", "geoplanet:7.6.0", "geoplanet:7.8.1", "geoplanet:7.9.0", "geoplanet:7.10.0", "geoplanet:8.0.0", "woeplanet:8.0.0"], "meta:indexed": "2020-08-20T20:56:08.197716", "woe:alias_FIN_V": ["Pamplonain Lentokentta", "Pamplonain Lentokentt\u00e4"], "woe:alias_ENG_V": ["PNA Airport", "PNA"], "woe:alias_ITA_V": ["Aeroporto Di Pamplonia"], "woe:alias_ENG_P": ["Pamplona Airport"], "woe:alias_DAN_V": ["Pamplona Lufthavn"], "woe:alias_UNK_V": ["Letiste Pamplona", "Letisko Pamplona"], "woe:alias_DUT_V": ["Luchthaven Pamplona"], "woe:alias_POR_V": ["Aeroporto de Pamplona"], "woe:alias_SWE_V": ["Pamplonas Flygplats"], "meta:updated": "2020-10-14T11:07:19.170619", "woe:alias_SPA_S": ["Aeropuerto de Pamplona-Noain"], "woe:alias_GER_V": ["Flughafen Pamplona"], "woe:alias_FRE_V": ["A\u00e9roport de Pamplune", "Aeroport de Pamplune"], "woe:alias_SPA_V": ["Aeropuerto de Noa\u00edn", "Aeropuerto de Noain", "Aeropuerto Pamplona-Noain", "Aeropuerto PNA", "PNA Aeropuerto", "Aeropuerto de Pamplona-Noain"], "woe:alias_FIN_S": ["Pamplonain Lentokentta"], "woe:alias_FRE_Q": ["A\u00e9roport de Pamplune"], "woe:alias_FIN_Q": ["Pamplonain Lentokentt\u00e4"], "woe:alias_DUT_Q": ["Luchthaven Pamplona"], "woe:alias_GER_Q": ["Flughafen Pamplona"], "woe:alias_FRE_S": ["Aeroport de Pamplune"], "woe:alias_POR_Q": ["Aeroporto de Pamplona"], "woe:alias_DAN_Q": ["Pamplona Lufthavn"], "woe:alias_SWE_Q": ["Pamplonas Flygplats"], "woe:alias_UNK_Q": ["Letiste Pamplona", "Letisko Pamplona"], "woe:alias_ITA_Q": ["Aeroporto Di Pamplonia"], "woe:hierarchy": {"continent": 24865675, "country": 23424950, "town": 0, "planet": 1, "county": 12602092, "suburb": 0, "state": 12578026, "region": 0, "localadmin": 12688361}, "woe:timezone_id": 56043644, "woe:hash": "ezwg69w4urm3", "woe:centroid": [-1.63952, 42.76754], "geom:latitude": 42.76754, "geom:longitude": -1.63952, "geom:hash": "ezwg69w4urm3", "woe:latitude": 42.76754, "geom:centroid": [-1.63952, 42.76754], "woe:longitude": -1.63952, "woe:repo": "woeplanet-airport-es", "geom:area": 0.0, "woe:scale": 19}}