{"type": "Feature", "id": 22656497, "geometry": {"type": "Point", "coordinates": [-5.64838, 42.587341]}, "properties": {"woe:id": 22656497, "woe:parent_id": 764226, "woe:name": "Aeropuerto Militar d\u00e9 Le\u00f3n", "woe:placetype": 14, "woe:placetype_name": "Airport", "woe:lang": "SPA", "iso:country": "ES", "meta:provider": ["geoplanet:7.3.1", "geoplanet:7.3.2", "geoplanet:7.4.0", "geoplanet:7.4.1", "geoplanet:7.5.1", "geoplanet:7.5.2", "geoplanet:7.6.0", "geoplanet:7.8.1", "geoplanet:7.9.0", "geoplanet:7.10.0", "geoplanet:8.0.0", "woeplanet:8.0.0"], "meta:indexed": "2020-08-20T20:56:08.181593", "meta:updated": "2020-10-14T11:07:19.137003", "woe:alias_SPA_S": ["Aeropuerto Militar de Leon"], "woe:hierarchy": {"continent": 24865675, "country": 23424950, "town": 0, "planet": 1, "county": 12602117, "suburb": 0, "state": 12578033, "region": 0, "localadmin": 12691922}, "woe:timezone_id": 56043644, "woe:hash": "ezefr2ycppy8", "woe:centroid": [-5.64838, 42.587341], "geom:latitude": 42.587341, "geom:longitude": -5.64838, "geom:hash": "ezefr2ycppy8", "woe:latitude": 42.587341, "geom:centroid": [-5.64838, 42.587341], "woe:longitude": -5.64838, "woe:repo": "woeplanet-airport-es", "geom:area": 0.0, "woe:scale": 19}}