{"type": "Feature", "id": 12523967, "properties": {"woe:id": 12523967, "woe:parent_id": 770966, "woe:name": "Aeropuerto de Puerto la Cruz", "woe:placetype": 14, "woe:placetype_name": "Airport", "woe:lang": "SPA", "iso:country": "ES", "meta:provider": ["geoplanet:7.3.1", "geoplanet:7.3.2", "geoplanet:7.4.0", "geoplanet:7.4.1", "geoplanet:7.5.1", "geoplanet:7.5.2", "geoplanet:7.6.0", "geoplanet:7.8.1", "geoplanet:7.9.0", "geoplanet:7.10.0", "geoplanet:8.0.0", "woeplanet:8.0.0"], "meta:indexed": "2020-08-20T20:56:08.171150", "woe:alias_ENG_V": ["UPC", "Pto la Cruz Airport", "UPC Airport"], "meta:updated": "2020-08-22T03:00:09.589146", "woe:alias_SPA_V": ["Aeropuerto UPC", "UPC Aeropuerto"], "woe:alias_ENG_P": ["Puerto La Cruz Airport"], "woe:hierarchy": {"continent": 24865675, "country": 23424950, "town": 0, "planet": 1, "county": 12602109, "suburb": 0, "state": 12578031, "region": 0, "localadmin": 12690185}, "woe:timezone_id": 28350870, "woe:hash": "eth1x6pkv95n", "woe:centroid": [-16.5462, 28.40048], "geom:latitude": 28.40048, "geom:longitude": -16.5462, "geom:hash": "eth1x6pkv95n", "woe:latitude": 28.40048, "geom:centroid": [-16.5462, 28.40048], "woe:longitude": -16.5462, "woe:repo": "woeplanet-airport-es"}, "geometry": {"coordinates": [-16.5462, 28.40048], "type": "Point"}}